awesome_sitemap_parser/__about__.py
awesome_sitemap_parser/__init__.py
awesome_sitemap_parser/exceptions.py
awesome_sitemap_parser/fetch_parse.py
awesome_sitemap_parser/helpers.py
awesome_sitemap_parser/log.py
awesome_sitemap_parser/objects/__init__.py
awesome_sitemap_parser/objects/page.py
awesome_sitemap_parser/objects/sitemap.py
awesome_sitemap_parser/tree.py
awesome_sitemap_parser/web_client/__init__.py
awesome_sitemap_parser/web_client/abstract_client.py
awesome_sitemap_parser/web_client/requests_client.py
awesome_sitemap_parser/web_client/zyte_client.py
awesome_sitemap_parser-0.1.0.dist-info/LICENSE
awesome_sitemap_parser-0.1.0.dist-info/METADATA
awesome_sitemap_parser-0.1.0.dist-info/WHEEL
awesome_sitemap_parser-0.1.0.dist-info/RECORD
